fp_admin/__init__.py
fp_admin/constants.py
fp_admin/exceptions.py
fp_admin/global_settings.py
fp_admin/settings_loader.py
fp_admin/admin/__init__.py
fp_admin/admin/apps/__init__.py
fp_admin/admin/apps/app_config.py
fp_admin/admin/apps/app_info.py
fp_admin/admin/fields/__init__.py
fp_admin/admin/fields/base.py
fp_admin/admin/fields/choices.py
fp_admin/admin/fields/errors.py
fp_admin/admin/fields/relationships.py
fp_admin/admin/fields/types.py
fp_admin/admin/fields/utils.py
fp_admin/admin/fields/validation.py
fp_admin/admin/fields/widgets.py
fp_admin/admin/models/__init__.py
fp_admin/admin/models/base.py
fp_admin/admin/views/__init__.py
fp_admin/admin/views/base.py
fp_admin/admin/views/builder.py
fp_admin/admin/views/factories.py
fp_admin/admin/views/registry.py
fp_admin/admin/views/types.py
fp_admin/api/__init__.py
fp_admin/api/middleware/__init__.py
fp_admin/api/schemas/__init__.py
fp_admin/api/v1/__init__.py
fp_admin/api/v1/apps_api.py
fp_admin/api/v1/views_api.py
fp_admin/apps/__init__.py
fp_admin/apps/auth/__init__.py
fp_admin/apps/auth/admin.py
fp_admin/apps/auth/apps.py
fp_admin/apps/auth/models.py
fp_admin/apps/auth/routers.py
fp_admin/apps/auth/views.py
fp_admin/cli/__init__.py
fp_admin/cli/main.py
fp_admin/cli/commands/__init__.py
fp_admin/cli/commands/database.py
fp_admin/cli/commands/project.py
fp_admin/cli/commands/system.py
fp_admin/cli/commands/user.py
fp_admin/cli/templates/startapp/admin.tpl
fp_admin/cli/templates/startapp/apps.tpl
fp_admin/cli/templates/startapp/models.tpl
fp_admin/cli/templates/startapp/routers.tpl
fp_admin/cli/templates/startapp/views.tpl
fp_admin/cli/templates/startproject/app.tpl
fp_admin/cli/templates/startproject/requirements.tpl
fp_admin/cli/templates/startproject/settings.tpl
fp_admin/core/__init__.py
fp_admin/core/database.py
fp_admin/core/loader.py
fp_admin/core/alembic_template/alembic.ini.mako
fp_admin/core/alembic_template/env.py
fp_admin/core/alembic_template/script.py.mako
fp_admin-0.0.6b0.dist-info/licenses/LICENSE
fp_admin-0.0.6b0.dist-info/METADATA
fp_admin-0.0.6b0.dist-info/WHEEL
fp_admin-0.0.6b0.dist-info/entry_points.txt
fp_admin-0.0.6b0.dist-info/top_level.txt
fp_admin-0.0.6b0.dist-info/RECORD
