Metadata-Version: 2.4
Name: fp-admin
Version: 0.0.6b0
Summary: FastAPI Admin
Author-email: Adel ESMAIRI <esmairi.github@gmail.com>
Maintainer: Rahma Bader
License-Expression: MIT
Project-URL: Homepage, https://github.com/esmairi/fp-admin
Project-URL: Repository, https://github.com/esmairi/fp-admin
Classifier: Development Status :: 5 - Production/Stable
Classifier: Intended Audience :: Developers
Classifier: Topic :: Software Development :: Libraries
Classifier: Programming Language :: Python :: 3.12
Classifier: Operating System :: OS Independent
Requires-Python: >=3.12
License-File: LICENSE
Requires-Dist: fastapi[standard]
Requires-Dist: pydantic-settings
Requires-Dist: sqlmodel
Requires-Dist: alembic
Requires-Dist: passlib[bcrypt]
Requires-Dist: uvicorn
Provides-Extra: dev
Requires-Dist: black==25.1.0; extra == "dev"
Requires-Dist: build==1.2.2.post1; extra == "dev"
Requires-Dist: flake8==7.3.0; extra == "dev"
Requires-Dist: httpx==0.28.1; extra == "dev"
Requires-Dist: mypy==1.16.1; extra == "dev"
Requires-Dist: mypy-extensions==1.1.0; extra == "dev"
Requires-Dist: pre-commit==4.2.0; extra == "dev"
Requires-Dist: pytest==8.4.1; extra == "dev"
Requires-Dist: pytest-cov==5.0.0; extra == "dev"
Requires-Dist: twine==6.1.0; extra == "dev"
Requires-Dist: bandit==1.7.8; extra == "dev"
Dynamic: license-file
